{
    "summary": {
        "BPU OPs per frame (effective)": 1108800,
        "BPU OPs per run (effective)": 1108800,
        "BPU PE number": 1,
        "BPU core number": 1,
        "BPU march": "B25E",
        "DDR bytes per frame": 19552256,
        "DDR bytes per run": 19552256,
        "DDR bytes per second": 6009998499,
        "DDR megabytes per frame": 18.646,
        "DDR megabytes per run": 18.646,
        "DDR megabytes per second": 5731.6,
        "FPS": 307.38,
        "HBDK version": "3.49.15",
        "compiling options": "-f hbir -m /tmp/tmplgy9l69e/torch_jit_subgraph_3.hbir -o /tmp/tmplgy9l69e/torch_jit_subgraph_3.hbm --march bayes-e --progressbar --O3 --debug --core-num 1 --fast --input-layout NHWC --output-layout NHWC --input-source ddr,ddr,ddr,ddr",
        "frame per run": 1,
        "frame per second": 307.38,
        "input features": [
            [
                "input name",
                "input size"
            ],
            [
                "/model.23/dfl/Softmax_output_0_reducesum_calibrated_quantized",
                "1x8400x4x1"
            ],
            [
                "/model.23/dfl/Softmax_output_0_exp_quantized",
                "1x4x16x8400"
            ],
            [
                "/model.23/Sigmoid_output_0_calibrated_Requantize_requantized_output",
                "1x1x1x8400"
            ],
            [
                "/model.23/ScatterND_2_output_0_calibrated_quantized",
                "1x1x72x8400"
            ]
        ],
        "interval computing unit utilization": [
            0.077,
            0.355,
            0.622,
            0.416,
            0.631,
            0.564,
            0.604,
            0.288,
            0.326,
            0.998,
            0.998,
            0.996,
            0.996,
            0.996,
            1.0,
            0.218,
            0.501,
            0.657,
            0.299,
            0.053,
            0.336,
            0.119,
            1.0,
            0.996,
            0.996,
            0.996,
            1.0,
            0.996,
            0.362,
            0.581,
            0.397,
            0.503,
            0.217
        ],
        "interval computing units utilization": [
            0.077,
            0.355,
            0.622,
            0.416,
            0.631,
            0.564,
            0.604,
            0.288,
            0.326,
            0.998,
            0.998,
            0.996,
            0.996,
            0.996,
            1.0,
            0.218,
            0.501,
            0.657,
            0.299,
            0.053,
            0.336,
            0.119,
            1.0,
            0.996,
            0.996,
            0.996,
            1.0,
            0.996,
            0.362,
            0.581,
            0.397,
            0.503,
            0.217
        ],
        "interval loading bandwidth (megabytes/s)": [
            6513,
            4121,
            2054,
            3032,
            4023,
            4520,
            4147,
            1809,
            2948,
            4101,
            3206,
            4101,
            3425,
            2050,
            676,
            1897,
            5126,
            4517,
            1287,
            0,
            0,
            2214,
            4101,
            3938,
            3714,
            2693,
            2437,
            2017,
            2337,
            4846,
            6162,
            6254,
            4053
        ],
        "interval number": 33,
        "interval storing bandwidth (megabytes/s)": [
            479,
            2563,
            2323,
            1780,
            4415,
            5382,
            5501,
            5333,
            2900,
            463,
            1025,
            1908,
            2050,
            1642,
            1025,
            1433,
            1455,
            1568,
            3629,
            5908,
            5777,
            3417,
            1058,
            1025,
            2050,
            1929,
            1025,
            1146,
            2050,
            1444,
            640,
            2256,
            3101
        ],
        "interval time (ms)": 0.1,
        "latency (ms)": 3.25,
        "latency (ms) by segments": [
            3.253
        ],
        "latency (us)": 3253.3,
        "layer details": [
            [
                "layer",
                "ops",
                "original output shape",
                "aligned output shape",
                "computing cost (no DDR)",
                "load/store cost",
                "active period of time"
            ],
            [
                "/model.23/dfl/Softmax_reciprocal_FROM_QUANTIZED_SOFTMAX",
                "0",
                "[1,4,1,8400]",
                "[1,4,8,8400]",
                "110 us (3.3% of model)",
                "9 us (0.2% of model)",
                "17 ~ 306 us (289)"
            ],
            [
                "/model.23/dfl/Softmax_mul_FROM_QUANTIZED_SOFTMAX",
                "0",
                "[1,4,16,8400]",
                "[1,4,16,8400]",
                "53 us (1.6% of model)",
                "399 us (12.2% of model)",
                "18 ~ 676 us (658)"
            ],
            [
                "/model.23/dfl/conv/Conv_NCHW2NHWC_LayoutConvert_Input0",
                "0",
                "[1,4,8400,16]",
                "[1,4,8448,16]",
                "38 us (1.1% of model)",
                "0",
                "362 ~ 682 us (320)"
            ],
            [
                "/model.23/dfl/conv/Conv",
                "1,075,200",
                "[1,4,8400,1]",
                "[1,4,8400,16]",
                "15 us (0.4% of model)",
                "9 us (0.2% of model)",
                "168 ~ 684 us (516)"
            ],
            [
                "/model.23/Slice",
                "0",
                "[1,2,8400,1]",
                "[1,2,8400,8]",
                "3 us (0% of model)",
                "0",
                "369 ~ 685 us (316)"
            ],
            [
                "/model.23/Slice_1",
                "0",
                "[1,2,8400,1]",
                "[1,2,8400,8]",
                "3 us (0% of model)",
                "0",
                "369 ~ 685 us (316)"
            ],
            [
                "/model.23/Sub",
                "0",
                "[1,2,8400,1]",
                "[1,2,8400,8]",
                "10 us (0.3% of model)",
                "57 us (1.7% of model)",
                "97 ~ 714 us (617)"
            ],
            [
                "/model.23/Add_10",
                "0",
                "[1,2,8400,1]",
                "[1,2,8400,8]",
                "10 us (0.3% of model)",
                "57 us (1.7% of model)",
                "94 ~ 709 us (615)"
            ],
            [
                "/model.23/Add_11",
                "0",
                "[1,2,8400,1]",
                "[1,2,8400,8]",
                "13 us (0.3% of model)",
                "13 us (0.3% of model)",
                "101 ~ 761 us (660)"
            ],
            [
                "/model.23/Div_1_mul",
                "33,600",
                "[1,2,8400,1]",
                "[1,2,8400,8]",
                "109 us (3.3% of model)",
                "299 us (9.2% of model)",
                "168 ~ 809 us (641)"
            ],
            [
                "/model.23/Div_1_mul_NHWC2NCHW_LayoutConvert_Output0_reshape",
                "0",
                "[1,1,2,8400]",
                "[1,1,2,8448]",
                "729 us (22.4% of model)",
                "600 us (18.4% of model)",
                "809 ~ 1733 us (924)"
            ],
            [
                "/model.23/Sub_1",
                "0",
                "[1,2,8400,1]",
                "[1,2,8400,8]",
                "110 us (3.3% of model)",
                "332 us (10.2% of model)",
                "1702 ~ 2130 us (428)"
            ],
            [
                "/model.23/Sub_1_NHWC2NCHW_LayoutConvert_Output0_reshape",
                "0",
                "[1,1,2,8400]",
                "[1,1,2,8448]",
                "729 us (22.4% of model)",
                "600 us (18.4% of model)",
                "2130 ~ 3054 us (924)"
            ],
            [
                "/model.23/Concat_28",
                "0",
                "[1,1,4,8400]",
                "[1,2,8,8400]",
                "9 us (0.2% of model)",
                "38 us (1.1% of model)",
                "2711 ~ 3083 us (372)"
            ],
            [
                "/model.23/Mul_5",
                "0",
                "[1,1,4,8400]",
                "[1,2,8,8400]",
                "13 us (0.4% of model)",
                "98 us (3.0% of model)",
                "2791 ~ 3228 us (437)"
            ],
            [
                "/model.23/Concat_35",
                "0",
                "[1,1,77,8400]",
                "[1,2,80,8400]",
                "65 us (2.0% of model)",
                "180 us (5.5% of model)",
                "3033 ~ 3253 us (220)"
            ]
        ],
        "loaded bytes per frame": 11106560,
        "loaded bytes per run": 11106560,
        "model json CRC": "023b26dd",
        "model json file": "/tmp/tmplgy9l69e/torch_jit_subgraph_3.hbir",
        "model name": "torch_jit_subgraph_3",
        "model param CRC": "00000000",
        "multicore sync time (ms)": 0.0,
        "run per second": 307.38,
        "runtime version": "3.15.55.0",
        "stored bytes per frame": 8445696,
        "stored bytes per run": 8445696,
        "worst FPS": 307.38
    }
}
