{
    "summary": {
        "BPU OPs per frame (effective)": 1108800,
        "BPU OPs per run (effective)": 1108800,
        "BPU PE number": 1,
        "BPU core number": 1,
        "BPU march": "B25E",
        "DDR bytes per frame": 18522592,
        "DDR bytes per run": 18522592,
        "DDR bytes per second": 5678073746,
        "DDR megabytes per frame": 17.665,
        "DDR megabytes per run": 17.665,
        "DDR megabytes per second": 5415.0,
        "FPS": 306.55,
        "HBDK version": "3.49.15",
        "compiling options": "-f hbir -m /tmp/tmptras1dsi/torch_jit_subgraph_1.hbir -o /tmp/tmptras1dsi/torch_jit_subgraph_1.hbm --march bayes-e --progressbar --O3 --debug --core-num 1 --fast --input-layout NHWC --output-layout NHWC --input-source ddr,ddr,ddr,ddr",
        "frame per run": 1,
        "frame per second": 306.55,
        "input features": [
            [
                "input name",
                "input size"
            ],
            [
                "/model.23/dfl/Softmax_output_0_reducesum_calibrated_quantized",
                "1x8400x4x1"
            ],
            [
                "/model.23/dfl/Softmax_output_0_exp_quantized",
                "1x4x16x8400"
            ],
            [
                "/model.23/Sigmoid_output_0_calibrated_Requantize_requantized_output",
                "1x1x1x8400"
            ],
            [
                "/model.23/Reshape_7_output_0_quantized",
                "1x1x72x8400"
            ]
        ],
        "interval computing unit utilization": [
            0.159,
            0.508,
            0.54,
            0.483,
            0.781,
            0.319,
            0.279,
            0.26,
            0.317,
            1.0,
            0.996,
            0.996,
            0.996,
            0.996,
            1.0,
            0.219,
            0.516,
            0.671,
            0.328,
            0.046,
            0.307,
            0.149,
            1.0,
            0.996,
            0.996,
            0.996,
            1.0,
            0.996,
            0.289,
            0.581,
            0.443,
            0.481,
            0.239
        ],
        "interval computing units utilization": [
            0.159,
            0.508,
            0.54,
            0.483,
            0.781,
            0.319,
            0.279,
            0.26,
            0.317,
            1.0,
            0.996,
            0.996,
            0.996,
            0.996,
            1.0,
            0.219,
            0.516,
            0.671,
            0.328,
            0.046,
            0.307,
            0.149,
            1.0,
            0.996,
            0.996,
            0.996,
            1.0,
            0.996,
            0.289,
            0.581,
            0.443,
            0.481,
            0.239
        ],
        "interval loading bandwidth (megabytes/s)": [
            6651,
            5027,
            3824,
            4282,
            4344,
            2449,
            270,
            7,
            2814,
            4102,
            3340,
            4101,
            3272,
            2050,
            828,
            1744,
            5072,
            3703,
            375,
            0,
            0,
            2317,
            4101,
            3835,
            3818,
            2796,
            2334,
            1946,
            2120,
            4596,
            6080,
            6188,
            4352
        ],
        "interval number": 33,
        "interval storing bandwidth (megabytes/s)": [
            0,
            495,
            1562,
            2082,
            3321,
            4890,
            5169,
            5210,
            3099,
            472,
            1025,
            2050,
            2050,
            1491,
            1025,
            1584,
            1455,
            1671,
            3629,
            5805,
            5880,
            3417,
            954,
            1025,
            2050,
            2031,
            1025,
            1044,
            2050,
            1455,
            640,
            1940,
            3101
        ],
        "interval time (ms)": 0.1,
        "latency (ms)": 3.26,
        "latency (ms) by segments": [
            3.262
        ],
        "latency (us)": 3262.1,
        "layer details": [
            [
                "layer",
                "ops",
                "original output shape",
                "aligned output shape",
                "computing cost (no DDR)",
                "load/store cost",
                "active period of time"
            ],
            [
                "/model.23/dfl/Softmax_reciprocal_FROM_QUANTIZED_SOFTMAX",
                "0",
                "[1,4,1,8400]",
                "[1,4,8,8400]",
                "110 us (3.3% of model)",
                "19 us (0.5% of model)",
                "11 ~ 341 us (330)"
            ],
            [
                "/model.23/dfl/Softmax_mul_FROM_QUANTIZED_SOFTMAX",
                "0",
                "[1,4,16,8400]",
                "[1,4,16,8400]",
                "48 us (1.4% of model)",
                "232 us (7.1% of model)",
                "14 ~ 353 us (339)"
            ],
            [
                "/model.23/dfl/conv/Conv_NCHW2NHWC_LayoutConvert_Input0",
                "0",
                "[1,4,8400,16]",
                "[1,4,8448,16]",
                "37 us (1.1% of model)",
                "79 us (2.4% of model)",
                "354 ~ 500 us (146)"
            ],
            [
                "/model.23/dfl/conv/Conv",
                "1,075,200",
                "[1,4,8400,1]",
                "[1,4,8400,16]",
                "14 us (0.4% of model)",
                "5 us (0.1% of model)",
                "218 ~ 504 us (286)"
            ],
            [
                "/model.23/Slice",
                "0",
                "[1,2,8400,1]",
                "[1,2,8400,8]",
                "3 us (0% of model)",
                "0",
                "381 ~ 583 us (202)"
            ],
            [
                "/model.23/Slice_1",
                "0",
                "[1,2,8400,1]",
                "[1,2,8400,8]",
                "3 us (0% of model)",
                "0",
                "380 ~ 582 us (202)"
            ],
            [
                "/model.23/Sub",
                "0",
                "[1,2,8400,1]",
                "[1,2,8400,8]",
                "9 us (0.2% of model)",
                "29 us (0.8% of model)",
                "112 ~ 728 us (616)"
            ],
            [
                "/model.23/Add_1",
                "0",
                "[1,2,8400,1]",
                "[1,2,8400,8]",
                "9 us (0.2% of model)",
                "29 us (0.8% of model)",
                "112 ~ 727 us (615)"
            ],
            [
                "/model.23/Add_2",
                "0",
                "[1,2,8400,1]",
                "[1,2,8400,8]",
                "12 us (0.3% of model)",
                "20 us (0.6% of model)",
                "118 ~ 879 us (761)"
            ],
            [
                "/model.23/Sub_1",
                "0",
                "[1,2,8400,1]",
                "[1,2,8400,8]",
                "111 us (3.3% of model)",
                "297 us (9.1% of model)",
                "118 ~ 810 us (692)"
            ],
            [
                "/model.23/Sub_1_NHWC2NCHW_LayoutConvert_Output0_reshape",
                "0",
                "[1,1,2,8400]",
                "[1,1,2,8448]",
                "729 us (22.3% of model)",
                "600 us (18.3% of model)",
                "812 ~ 1737 us (925)"
            ],
            [
                "/model.23/Div_1_mul",
                "33,600",
                "[1,2,8400,1]",
                "[1,2,8400,8]",
                "108 us (3.3% of model)",
                "300 us (9.1% of model)",
                "1706 ~ 2127 us (421)"
            ],
            [
                "/model.23/Div_1_mul_NHWC2NCHW_LayoutConvert_Output0_reshape",
                "0",
                "[1,1,2,8400]",
                "[1,1,2,8448]",
                "729 us (22.3% of model)",
                "600 us (18.3% of model)",
                "2127 ~ 3051 us (924)"
            ],
            [
                "/model.23/Concat_5",
                "0",
                "[1,1,4,8400]",
                "[1,2,8,8400]",
                "9 us (0.2% of model)",
                "38 us (1.1% of model)",
                "2705 ~ 3094 us (389)"
            ],
            [
                "/model.23/Mul_2",
                "0",
                "[1,1,4,8400]",
                "[1,2,8,8400]",
                "13 us (0.4% of model)",
                "98 us (3.0% of model)",
                "2789 ~ 3237 us (448)"
            ],
            [
                "/model.23/Concat_7",
                "0",
                "[1,1,77,8400]",
                "[1,2,80,8400]",
                "65 us (2.0% of model)",
                "180 us (5.5% of model)",
                "3030 ~ 3262 us (232)"
            ]
        ],
        "loaded bytes per frame": 10544224,
        "loaded bytes per run": 10544224,
        "model json CRC": "fde55734",
        "model json file": "/tmp/tmptras1dsi/torch_jit_subgraph_1.hbir",
        "model name": "torch_jit_subgraph_1",
        "model param CRC": "00000000",
        "multicore sync time (ms)": 0.0,
        "run per second": 306.55,
        "runtime version": "3.15.55.0",
        "stored bytes per frame": 7978368,
        "stored bytes per run": 7978368,
        "worst FPS": 306.55
    }
}
